{
  "columns": [
    { "name": "TimeGenerated", "type": "datetime" },
    { "name": "Data", "type": "string", "values": [
      "{\"EVENT_ID\":10001,\"EVENT_TIMESTAMP\":\"2025-01-15T14:22:00.000Z\",\"EVENT_TYPE\":\"LOGIN\",\"USER_NAME\":\"JSMITH\",\"CLIENT_IP\":\"10.0.1.50\",\"REPORTED_CLIENT_TYPE\":\"SNOWFLAKE_UI\",\"REPORTED_CLIENT_VERSION\":\"1.0\",\"FIRST_AUTHENTICATION_FACTOR\":\"PASSWORD\",\"SECOND_AUTHENTICATION_FACTOR\":\"DUO_PUSH\",\"IS_SUCCESS\":\"YES\",\"ERROR_CODE\":null,\"ERROR_MESSAGE\":null}",
      "{\"EVENT_ID\":10002,\"EVENT_TIMESTAMP\":\"2025-01-15T15:10:00.000Z\",\"EVENT_TYPE\":\"LOGIN\",\"USER_NAME\":\"AGARCIA\",\"CLIENT_IP\":\"203.0.113.42\",\"REPORTED_CLIENT_TYPE\":\"JDBC_DRIVER\",\"REPORTED_CLIENT_VERSION\":\"3.14.4\",\"FIRST_AUTHENTICATION_FACTOR\":\"PASSWORD\",\"SECOND_AUTHENTICATION_FACTOR\":null,\"IS_SUCCESS\":\"NO\",\"ERROR_CODE\":390100,\"ERROR_MESSAGE\":\"Incorrect username or password was specified.\"}",
      "{\"EVENT_ID\":10003,\"EVENT_TIMESTAMP\":\"2025-01-15T09:45:00.000Z\",\"EVENT_TYPE\":\"LOGIN\",\"USER_NAME\":\"SVC_ETL\",\"CLIENT_IP\":\"10.0.2.10\",\"REPORTED_CLIENT_TYPE\":\"PYTHON_DRIVER\",\"REPORTED_CLIENT_VERSION\":\"3.6.0\",\"FIRST_AUTHENTICATION_FACTOR\":\"RSA_KEYPAIR\",\"SECOND_AUTHENTICATION_FACTOR\":null,\"IS_SUCCESS\":\"YES\",\"ERROR_CODE\":null,\"ERROR_MESSAGE\":null}",
      "{\"EVENT_ID\":10004,\"EVENT_TIMESTAMP\":\"2025-01-15T20:30:00.000Z\",\"EVENT_TYPE\":\"LOGIN\",\"USER_NAME\":\"ADMIN\",\"CLIENT_IP\":\"198.51.100.17\",\"REPORTED_CLIENT_TYPE\":\"SNOWSQL\",\"REPORTED_CLIENT_VERSION\":\"1.2.32\",\"FIRST_AUTHENTICATION_FACTOR\":\"PASSWORD\",\"SECOND_AUTHENTICATION_FACTOR\":\"DUO_PASSCODE\",\"IS_SUCCESS\":\"YES\",\"ERROR_CODE\":null,\"ERROR_MESSAGE\":null}",
      "{\"EVENT_ID\":10005,\"EVENT_TIMESTAMP\":\"2025-01-16T03:15:00.000Z\",\"EVENT_TYPE\":\"LOGIN\",\"USER_NAME\":\"MWILSON\",\"CLIENT_IP\":\"100.21.55.130\",\"REPORTED_CLIENT_TYPE\":\"ODBC_DRIVER\",\"REPORTED_CLIENT_VERSION\":\"3.3.2\",\"FIRST_AUTHENTICATION_FACTOR\":\"OAUTH_ACCESS_TOKEN\",\"SECOND_AUTHENTICATION_FACTOR\":null,\"IS_SUCCESS\":\"YES\",\"ERROR_CODE\":null,\"ERROR_MESSAGE\":null}",
      "{\"EVENT_ID\":10006,\"EVENT_TIMESTAMP\":\"2025-01-15T11:00:00.000Z\",\"EVENT_TYPE\":\"LOGIN\",\"USER_NAME\":\"UNKNOWN_USER\",\"CLIENT_IP\":\"203.0.113.42\",\"REPORTED_CLIENT_TYPE\":\"JAVASCRIPT_DRIVER\",\"REPORTED_CLIENT_VERSION\":\"1.9.3\",\"FIRST_AUTHENTICATION_FACTOR\":\"PASSWORD\",\"SECOND_AUTHENTICATION_FACTOR\":null,\"IS_SUCCESS\":\"NO\",\"ERROR_CODE\":390100,\"ERROR_MESSAGE\":\"Incorrect username or password was specified.\"}"
    ] }
  ]
}
